Metadata-Version: 2.1
Name: pyPWD
Version: 1.0.0
Summary: A simple password generator
Home-page: https://github.com/HYKANTUS/pyPWD
Author: HYKANTUS
Author-email: hykantus@gmail.com
License: UNKNOWN
Project-URL: Personal Website, http://hykantus.tk/
Keywords: password,passwords,password generator,security
Platform: UNKNOWN
Classifier: Development Status :: 5 - Production/Stable
Classifier: Intended Audience :: Developers
Classifier: Topic :: Software Development :: Build Tools
Classifier: License :: OSI Approved :: MIT License
Classifier: Programming Language :: Python :: 3
Classifier: Programming Language :: Python :: 3.6
Classifier: Programming Language :: Python :: 3.7
Classifier: Programming Language :: Python :: 3.8
Classifier: Programming Language :: Python :: 3.9
Classifier: Programming Language :: Python :: 3 :: Only
Requires-Python: >=3.6, <4
